kynegos_easy_cloud/Download_Catastro_Spain.py
kynegos_easy_cloud/Kynegos_Easy_Plus_Functions.py
kynegos_easy_cloud/Kynegos_GIS_functions.py
kynegos_easy_cloud/Kynegos_functions.py
kynegos_easy_cloud/__init__.py
kynegos_easy_cloud-1.4.8.dist-info/licenses/LICENSE
kynegos_easy_cloud-1.4.8.dist-info/METADATA
kynegos_easy_cloud-1.4.8.dist-info/WHEEL
kynegos_easy_cloud-1.4.8.dist-info/top_level.txt
kynegos_easy_cloud-1.4.8.dist-info/RECORD
