Metadata-Version: 2.4
Name: kynegos_easy_cloud
Version: 1.4.8
Summary: Kynegos Easy Cloud: automatiza Google Cloud para equipos de datos sin DevOps
Home-page: https://kynegos.com/
Author: Kynegos <> Data Hub
Author-email: digital.data@capitalenergy.com
License: Kynegos License
Project-URL: PyPI, https://pypi.org/project/kynegos-easy-cloud/
Project-URL: LinkedIn, https://www.linkedin.com/company/kynegos/
Project-URL: X, https://x.com/Kynegos_
Project-URL: Documentación, https://kynegos.com/
Keywords: Kynegos,kynegos easy cloud,Google Cloud,BigQuery,GCS,Python,Data Engineering,automatización cloud,catastro,GIS,GIS BigQuery,GIS Cloud
Classifier: Development Status :: 5 - Production/Stable
Classifier: Intended Audience :: Developers
Classifier: Topic :: Software Development :: Libraries :: Python Modules
Classifier: Topic :: Utilities
Classifier: Programming Language :: Python :: 3
Classifier: Programming Language :: Python :: 3.8
Classifier: Programming Language :: Python :: 3.9
Classifier: Programming Language :: Python :: 3.10
Classifier: License :: Other/Proprietary License
Classifier: Operating System :: OS Independent
Requires-Python: >=3.6
License-File: LICENSE
Requires-Dist: google-auth
Requires-Dist: google-cloud-bigquery
Requires-Dist: google-cloud-storage
Requires-Dist: google-cloud-aiplatform
Requires-Dist: pandas
Requires-Dist: atoma
Requires-Dist: geopandas
Requires-Dist: db-dtypes
Requires-Dist: shapely
Requires-Dist: owslib
Dynamic: author
Dynamic: author-email
Dynamic: classifier
Dynamic: description
Dynamic: description-content-type
Dynamic: home-page
Dynamic: keywords
Dynamic: license
Dynamic: license-file
Dynamic: project-url
Dynamic: requires-dist
Dynamic: requires-python
Dynamic: summary
